[{"title":"那些成功者都有一套自己的筆記規則 : 活用64張圖,讓手帳一目暸然的歸納整理術!","record_num":"1359759","placed_gmt":"2017-03-08 08:54:01+08","pickup_location_code":"1","call_number":"|d019.2|e2274","call_number_norm":"019.2 2274","barcode":"30010101616632"},{"title":"正是時候讀莊子. 二, 人情 = Zhuangzi","record_num":"1359642","placed_gmt":"2017-04-06 08:23:09+08","pickup_location_code":"1","call_number":"|d121.337|e4472","call_number_norm":"121.337 4472","barcode":"30010101655572"},{"title":"羅爾斯與《正義論》 顧肅, 劉雪梅譯","record_num":"1234455","placed_gmt":"2017-04-19 15:53:07+08","pickup_location_code":"1","call_number":"|d145.8|e2647","call_number_norm":"145.8 2647","barcode":"30010101589912"},{"title":"為什麼我們總是相信自己是對的? : 不知不覺掉入的101種慣性思考陷阱","record_num":"1360636","placed_gmt":"2017-04-11 21:05:50+08","pickup_location_code":"1","call_number":"|d176.3|e4048","call_number_norm":"176.3 4048","barcode":"30010101658568"},{"title":"不被情緒左右的28個練習","record_num":"1354384","placed_gmt":"2017-03-25 16:22:17+08","pickup_location_code":"1","call_number":"|d176.52|e1265","call_number_norm":"176.52 1265","barcode":"30010101615154"},{"title":"你要如何衡量你的人生 廖月娟譯","record_num":"1268726","placed_gmt":"2017-03-24 17:29:22+08","pickup_location_code":"1","call_number":"|d177.2|e4643","call_number_norm":"177.2 4643","barcode":"30010101136524"},{"title":"神經神學 : 宗教有腦生物基礎嗎? = Neurotheology","record_num":"1359491","placed_gmt":"2017-04-18 10:08:43+08","pickup_location_code":"1","call_number":"|d200.16|e2537-1","call_number_norm":"200.16 2537 1","barcode":"30010101620634"},{"title":"你所煩惱的事,有九成都不會發生","record_num":"1341159","placed_gmt":"2016-12-15 00:13:56+08","pickup_location_code":"1","call_number":"|d226.6|e4626","call_number_norm":"226.6 4626","barcode":"30010101295098"},{"title":"我們從未現代過 余曉嵐, 林文源, 許全義譯","record_num":"1280244","placed_gmt":"2017-04-08 09:37:55+08","pickup_location_code":"1","call_number":"|d301|e5061-1","call_number_norm":"301 5061 1","barcode":"30010101379405"},{"title":"Python+ Spark 2.0+ Hadoop機器學習與大數據分析實戰","record_num":"1358818","placed_gmt":"2017-03-30 21:54:37+08","pickup_location_code":"1","call_number":"|d312.136|e4445 2016","call_number_norm":"312.136 4445 2016","barcode":"30010101615493"},{"title":"存活分析","record_num":"1153157","placed_gmt":"2017-04-20 16:40:25+08","pickup_location_code":"1","call_number":"|d360.13|e4415","call_number_norm":"360.13 4415","barcode":"30010100709149"},{"title":"趣味簡明臨床微生物學 蕭孟芳譯","record_num":"1293337","placed_gmt":"2017-04-01 18:30:17+08","pickup_location_code":"1","call_number":"|d369.8|e4423|y2013","call_number_norm":"369.8 4423 2013","barcode":"30010101480773"},{"title":"菜醫師,借過一下 : 克拉克見習日誌","record_num":"1359981","placed_gmt":"2017-03-13 09:05:47+08","pickup_location_code":"1","call_number":"|d410.3|e4060 2017","call_number_norm":"410.3 4060 2017","barcode":"30010101655929"},{"title":"站在器官移植前線 : 一個肝臟移植醫師挑戰極限、修復生命、見證醫療突破的現場故事","record_num":"1360391","placed_gmt":"2017-03-29 09:10:32+08","pickup_location_code":"1","call_number":"|d410.9952|e4422 2017","call_number_norm":"410.9952 4422 2017","barcode":"30010101658055"},{"title":"彼拉提斯解剖書 王怡璇譯","record_num":"1272158","placed_gmt":"2017-04-20 22:20:29+08","pickup_location_code":"1","call_number":"|d411.71|e4134","call_number_norm":"411.71 4134","barcode":"30010101391632"},{"title":"愈睡愈成功 揮別疲憊的生活,從充足睡眠開啟自信人生","record_num":"1358831","placed_gmt":"2017-02-26 12:14:42+08","pickup_location_code":"1","call_number":"|d411.77|e6841 2016","call_number_norm":"411.77 6841 2016","barcode":"30010101655382"},{"title":"核子醫學","record_num":"1151433","placed_gmt":"2017-04-24 12:22:15+08","pickup_location_code":"1","call_number":"|d415.216|e1093","call_number_norm":"415.216 1093","barcode":"30010100687865"},{"title":"放射治療物理學","record_num":"1353340","placed_gmt":"2017-03-16 20:19:08+08","pickup_location_code":"1","call_number":"|d415.216|e2100 2016","call_number_norm":"415.216 2100 2016","barcode":"30010101624172"},{"title":"分子輻射生物學 洪世凱, 黃正仲主譯","record_num":"1302304","placed_gmt":"2017-04-22 16:55:01+08","pickup_location_code":"1","call_number":"|d415.216|e4710|y2013","call_number_norm":"415.216 4710 2013","barcode":"30010101402843"},{"title":"急診鋼鐵人2.0戰鬥吧!護理師 : 一同體驗忙到「瘦」死、超時、超量、超爆肝的護理人生!","record_num":"1359663","placed_gmt":"2017-02-26 12:12:01+08","pickup_location_code":"1","call_number":"|d415.22|e2072-1 2017","call_number_norm":"415.22 2072 1 2017","barcode":"30010101655721"},{"title":"1日5分鐘,搞定自律神經失調","record_num":"1302843","placed_gmt":"2017-03-31 21:19:21+08","pickup_location_code":"1","call_number":"|d415.943|e2448|y2013","call_number_norm":"415.943 2448 2013","barcode":"30010101408626"},{"title":"人際過敏症 : 曾經良好的關係,為什麼突然改變? = Human allergies","record_num":"1354377","placed_gmt":"2016-12-24 11:42:58+08","pickup_location_code":"1","call_number":"|d415.994|e7681 2016","call_number_norm":"415.994 7681 2016","barcode":"30010101616269"},{"title":"下背痛教室 林宜潔譯","record_num":"1332401","placed_gmt":"2017-04-11 16:43:25+08","pickup_location_code":"1","call_number":"|d416.616|e2220|y2015 ","call_number_norm":"416.616 2220 2015","barcode":"30010101191222"},{"title":"放射藥品學 丁慧枝編譯","record_num":"1331842","placed_gmt":"2017-04-15 14:46:55+08","pickup_location_code":"1","call_number":"|d418|e3968|y2011","call_number_norm":"418 3968 2011","barcode":"30010101188178"},{"title":"動作控制與學習","record_num":"1332406","placed_gmt":"2017-05-01 15:31:56+08","pickup_location_code":"1","call_number":"|d418.93|e0832 2015","call_number_norm":"418.93 0832 2015","barcode":"30010101191297"},{"title":"有一個銀蛋叫彼得,從小生在大醫院 : 借學分、逃兵役，戴鋼盔赴晨會的實習血淚","record_num":"1360623","placed_gmt":"2017-04-11 17:12:26+08","pickup_location_code":"1","call_number":"|d419.47|e2343-2 2017","call_number_norm":"419.47 2343 2 2017","barcode":"30010101658477"},{"title":"醫療責任的形成與展開","record_num":"1326802","placed_gmt":"2017-04-19 13:30:22+08","pickup_location_code":"1","call_number":"|d419.49|e7513-1|y2014","call_number_norm":"419.49 7513 1 2014","barcode":"30010101442187"},{"title":"美姿美儀 : 時尚優雅美麗聖經","record_num":"1334864","placed_gmt":"2017-04-13 09:37:06+08","pickup_location_code":"1","call_number":"|d425.8|e2884","call_number_norm":"425.8 2884","barcode":"30010101237454"},{"title":"社群分享經濟的力量 : 把分享打造成新型態的購買，推特、臉書、Linkedin、Instagram、Youtube的人本分享術","record_num":"1354380","placed_gmt":"2017-02-24 10:45:43+08","pickup_location_code":"1","call_number":"|d490.29|e4051","call_number_norm":"490.29 4051","barcode":"30010101615121"},{"title":"思辨賽局 : 看穿局勢、創造優勢的策略智慧","record_num":"1344504","placed_gmt":"2017-03-19 10:04:43+08","pickup_location_code":"1","call_number":"|d494.1|e4442.2","call_number_norm":"494.1 4442.2","barcode":"30010101608563"},{"title":"強習慣 : 工作效率提升120%、30歲前擁有9間公司的關鍵","record_num":"1360388","placed_gmt":"2017-03-28 11:24:35+08","pickup_location_code":"1","call_number":"|d494.35|e9211","call_number_norm":"494.35 9211","barcode":"30010101658147"},{"title":"醫護統計與SPSS","record_num":"1334288","placed_gmt":"2017-04-24 14:40:00+08","pickup_location_code":"1","call_number":"|d512.4|e4627","call_number_norm":"512.4 4627","barcode":"30010101174053"},{"title":"父母家的斷捨離 : 囤積狂與斷捨離主義者的對決","record_num":"1360390","placed_gmt":"2017-03-31 16:16:15+08","pickup_location_code":"1","call_number":"|d528.2|e2141","call_number_norm":"528.2 2141","barcode":"30010101658139"},{"title":"ACSM運動測試與運動處方指引","record_num":"1289354","placed_gmt":"2017-04-11 09:17:51+08","pickup_location_code":"1","call_number":"|d528.9016|e4444","call_number_norm":"528.9016 4444","barcode":"30010101151432"},{"title":"就是愛挑戰!我的第一本路跑書 : 從選鞋、體態練習、防護運動、訓練計畫到挑戰馬拉松","record_num":"1342105","placed_gmt":"2017-03-08 13:48:37+08","pickup_location_code":"1","call_number":"|d528.946|e5272-1","call_number_norm":"528.946 5272 1","barcode":"30010101300930"},{"title":"逃難吧……戰地記者喬裝敘利亞難民168hr偷渡紀實","record_num":"1360639","placed_gmt":"2017-04-12 01:00:54+08","pickup_location_code":"1","call_number":"|d542.277|e2710","call_number_norm":"542.277 2710","barcode":"30010101658626"},{"title":"學著,好好愛","record_num":"1341414","placed_gmt":"2017-03-19 21:46:36+08","pickup_location_code":"1","call_number":"|d544.37|e1257","call_number_norm":"544.37 1257","barcode":"30010101297607"},{"title":"麥克風的股市求生手冊","record_num":"1331781","placed_gmt":"2017-04-11 08:30:17+08","pickup_location_code":"1","call_number":"|d563.53|e4047","call_number_norm":"563.53 4047","barcode":"30010101186594"},{"title":"新疆玩全攻略","record_num":"1332907","placed_gmt":"2017-04-16 12:31:25+08","pickup_location_code":"1","call_number":"|d676.169|e0118|y2014","call_number_norm":"676.169 0118 2014","barcode":"30010101470428"},{"title":"世界上不可能存在的地方 / : 51個世界上最不尋常的地點","record_num":"1358370","placed_gmt":"2017-02-20 15:11:18+08","pickup_location_code":"1","call_number":"|d716.9|e4423 2016","call_number_norm":"716.9 4423 2016","barcode":"30010101618778"},{"title":"東京旅遊全攻略 2015-16年版","record_num":"1337208","placed_gmt":"2017-04-23 16:08:39+08","pickup_location_code":"1","call_number":"|d731.72609|e8731|y2015","call_number_norm":"731.72609 8731 2015","barcode":"30010101247990"},{"title":"搭地鐵玩遍首爾","record_num":"1345389","placed_gmt":"2017-02-16 14:59:08+08","pickup_location_code":"1","call_number":"|d732.7609|e4073 2016","call_number_norm":"732.7609 4073 2016","barcode":"30010101609785"},{"title":"TED talks說話的力量 : 你可以用言語來改變自己，也改變世界","record_num":"1344353","placed_gmt":"2017-02-04 15:57:41+08","pickup_location_code":"1","call_number":"|d811.9|e3022","call_number_norm":"811.9 3022","barcode":"30010101602087"},{"title":"故事寫作大師班 : 好萊塢知名「劇本醫生」教你STEP BY STEP寫出絕不跟別人撞哏、兼具情感厚度與立體結構的最強故事","record_num":"1342038","placed_gmt":"2017-04-19 11:18:20+08","pickup_location_code":"1","call_number":"|d812.31|e2422","call_number_norm":"812.31 2422","barcode":"30010101301458"},{"title":"請問侯文詠","record_num":"1330443","placed_gmt":"2017-02-15 15:33:50+08","pickup_location_code":"1","call_number":"|d855|e2700-10","call_number_norm":"855 2700 10","barcode":"30010101179573"},{"title":"青春瑣事之樹","record_num":"1342024","placed_gmt":"2017-04-28 22:47:30+08","pickup_location_code":"1","call_number":"|d855|e4437.3-1","call_number_norm":"855 4437.3 1","barcode":"30010101301441"},{"title":"文藝女青年這種病,生個孩子就好了","record_num":"1345275","placed_gmt":"2017-02-17 12:24:56+08","pickup_location_code":"1","call_number":"|d855|e4480.1","call_number_norm":"855 4480.1","barcode":"30010101627621"},{"title":"從你的全世界路過","record_num":"1332109","placed_gmt":"2017-03-08 15:02:58+08","pickup_location_code":"1","call_number":"|d857.63|e1142","call_number_norm":"857.63 1142","barcode":"30010101188335"},{"title":"我是許涼涼","record_num":"1220087","placed_gmt":"2017-05-01 11:18:51+08","pickup_location_code":"1","call_number":"|d857.63|e4024.1","call_number_norm":"857.63 4024.1","barcode":"30010101093220"},{"title":"流","record_num":"1343931","placed_gmt":"2016-11-21 17:38:58+08","pickup_location_code":"1","call_number":"|d861.57|e5203","call_number_norm":"861.57 5203","barcode":"30010101258005"},{"title":"吉祥寺的朝日奈君","record_num":"1354371","placed_gmt":"2017-04-14 03:15:23+08","pickup_location_code":"1","call_number":"|a861.57|e5631","call_number_norm":"861.57 5631","barcode":"30010101615097"},{"title":"解憂雜貨店 王蘊潔譯","record_num":"1291750","placed_gmt":"2016-09-30 19:34:39+08","pickup_location_code":"1","call_number":"|d861.57|e5641-50","call_number_norm":"861.57 5641 50","barcode":"30010101500273"},{"title":"杜鵑鳥的蛋是誰的 王華懋譯","record_num":"1302185","placed_gmt":"2017-04-26 12:12:05+08","pickup_location_code":"1","call_number":"|d861.57|e5641-52","call_number_norm":"861.57 5641 52","barcode":"30010101407214"},{"title":"人魚沉睡的家","record_num":"1358742","placed_gmt":"2017-02-09 15:19:45+08","pickup_location_code":"1","call_number":"|d861.57|e5641-73","call_number_norm":"861.57 5641 73","barcode":"30010101637786"},{"title":"列車上的女孩 王欣欣譯","record_num":"1334661","placed_gmt":"2016-09-20 22:26:34+08","pickup_location_code":"1","call_number":"|d873.57|e4444.7","call_number_norm":"873.57 4444.7","barcode":"30010101231937"},{"title":"世界絕美宮殿蒐藏 = Beautiful palaces in the world","record_num":"1341954","placed_gmt":"2017-04-01 16:04:14+08","pickup_location_code":"1","call_number":"|d924|e5280","call_number_norm":"924 5280","barcode":"30010101300856"},{"title":"大人的紓壓摺學 : 用一張色紙輕鬆打造我的紙上動物園","record_num":"1359762","placed_gmt":"2017-03-09 11:38:58+08","pickup_location_code":"1","call_number":"|d972.1|e3531","call_number_norm":"972.1 3531","barcode":"30010101615220"},{"title":"全新!黃金認證New TOEIC新多益聽力模擬試題","record_num":"1354339","placed_gmt":"2017-04-05 16:45:40+08","pickup_location_code":"1","call_number":"|pAP|d805.1895|e4453 2016","call_number_norm":"ap  805.1895 4453 2016","barcode":"30010101628835"},{"title":"全新!黃金認證New TOEIC新多益閱讀模擬試題","record_num":"1354338","placed_gmt":"2017-03-06 10:39:58+08","pickup_location_code":"1","call_number":"|pAP|d805.1895|e8048.1 2016","call_number_norm":"ap  805.1895 8048 1 2016","barcode":"30010101628827"},{"title":"The brain : an introduction to functional neuroanatomy","record_num":"1241297","placed_gmt":"2017-04-09 20:04:06+08","pickup_location_code":"1","call_number":"|aWL300|bW337 2010","call_number_norm":"wl  300 w337 2010","barcode":"30020100924713"},{"title":"Analytical chemistry","record_num":"1325014","placed_gmt":"2017-02-16 17:40:31+08","pickup_location_code":"1","call_number":null,"call_number_norm":null,"barcode":"30020100859422"},{"title":"The cell : a molecular approach","record_num":"1341887","placed_gmt":"2017-04-17 13:10:36+08","pickup_location_code":"1book","call_number":null,"call_number_norm":null,"barcode":"30020100768920"},{"title":"惡女訂製服 [錄影資料] = The Dressmaker","record_num":"1359934","placed_gmt":"2017-04-02 22:29:37+08","pickup_location_code":"1","call_number":"|pVV-H|d987.83|e1402","call_number_norm":"h   987.83 1402","barcode":"30020200252627"},{"title":"一路有你 [錄影資料] = The road less traveled","record_num":"1360389","placed_gmt":"2017-04-24 16:43:44+08","pickup_location_code":"1","call_number":"|pVV-H|d987.83|e1624","call_number_norm":"h   987.83 1624","barcode":"30020200291146"},{"title":"中央情爆員 [錄影資料] = Central intelligence","record_num":"1360397","placed_gmt":"2017-04-24 16:41:43+08","pickup_location_code":"1","call_number":"|pVV-H|d987.83|e5599","call_number_norm":"h   987.83 5599","barcode":"30020200292896"},{"title":"A theory of justice","record_num":"1090684","placed_gmt":"2017-04-19 15:52:26+08","pickup_location_code":"1","call_number":"|aJC578|bR261 1999","call_number_norm":"jc  578 r261 1999","barcode":"30020100240532"},{"title":"我就要你好好的 [錄影資料] = Me before you","record_num":"1358850","placed_gmt":"2017-03-09 18:57:47+08","pickup_location_code":"1","call_number":"|pVV|d987.83|e2012.1","call_number_norm":"vv  987.83 2012 1","barcode":"30020200290015"},{"title":"革命前夕的摩托車日記","record_num":"1121493","placed_gmt":"2017-04-17 19:16:09+08","pickup_location_code":"1book","call_number":"|pVV|d987.83|e4882","call_number_norm":"vv  987.83 4882","barcode":"30020200113795"},{"title":"靈界的譯者","record_num":"1208442","placed_gmt":"2017-04-21 02:25:33+08","pickup_location_code":"4","call_number":"|d296.1|e4011","call_number_norm":"296.1 4011","barcode":"30010101058066"},{"title":"靈界的譯者. 3. 情與愛的輪迴","record_num":"1347896","placed_gmt":"2017-04-21 02:25:13+08","pickup_location_code":"4","call_number":"|d296.1|e4011-2","call_number_norm":"296.1 4011 2","barcode":"30010101628280"},{"title":"瘦腹運動","record_num":"1301785","placed_gmt":"2017-04-24 16:04:42+08","pickup_location_code":"4","call_number":"|d425.2|e7729","call_number_norm":"425.2 7729","barcode":"30010101161811"},{"title":"平行世界的愛情故事","record_num":"1345901","placed_gmt":"2016-11-22 17:53:58+08","pickup_location_code":"4","call_number":"|d861.57|e5641-71","call_number_norm":"861.57 5641 71","barcode":"30010101603960"},{"title":"料理的科學 陳維真,張簡守展等合譯","record_num":"1339237","placed_gmt":"2017-03-20 16:20:38+08","pickup_location_code":"4ilan","call_number":null,"call_number_norm":null,"barcode":"30010101284498"}]